spacy_ray/__init__.py
spacy_ray/loggers.py
spacy_ray/proxies.py
spacy_ray/train_cli.py
spacy_ray/util.py
spacy_ray/worker.py
spacy_ray/tests/__init__.py
spacy_ray/tests/mock_ray.py
spacy_ray/tests/test_worker.py
spacy_ray-0.1.4.dist-info/LICENSE
spacy_ray-0.1.4.dist-info/METADATA
spacy_ray-0.1.4.dist-info/WHEEL
spacy_ray-0.1.4.dist-info/entry_points.txt
spacy_ray-0.1.4.dist-info/top_level.txt
spacy_ray-0.1.4.dist-info/zip-safe
spacy_ray-0.1.4.dist-info/RECORD
